{"trancadas":[{"nome":"Estru Dados","nota":0,"carga":64,"semestre":2}],"completas":[{"nome":"Fundamentos de Programação","nota":10,"carga":96,"semestre":1},{"nome":"Introdução a Ciên...","nota":8.6,"carga":64,"semestre":1},{"nome":"TGA","nota":9.5,"carga":64,"semestre":1},{"nome":"Matemática Básica","nota":7.9,"carga":64,"semestre":1},{"nome":"Pré-Cálculo","nota":7.3,"carga":32,"semestre":1},{"nome":"Arquitetura de Computadores","nota":7,"carga":64,"semestre":2},{"nome":"Cálculo 1","nota":7.4,"carga":64,"semestre":2},{"nome":"POO","nota":9.4,"carga":64,"semestre":2},{"nome":"Mat Discreta","nota":8.7,"carga":64,"semestre":2},{"nome":"TGS","nota":8.3,"carga":64,"semestre":2},{"nome":"Estru Dados","nota":7.7,"carga":64,"semestre":3},{"nome":"FBD","nota":8.3,"carga":64,"semestre":3},{"nome":"PE","nota":8.5,"carga":64,"semestre":3},{"nome":"SO","nota":7.2,"carga":64,"semestre":3},{"nome":"Introd. CG","nota":9.2,"carga":64,"semestre":3}]}